<annotation>
	<folder>JPEGImages</folder>
	<filename>000032.jpg</filename>
	<path>D:\windows_v1.6.1\JPEGImages\000032.jpg</path>
	<source>
		<database>Unknown</database>
	</source>
	<size>
		<width>600</width>
		<height>420</height>
		<depth>3</depth>
	</size>
	<segmented>0</segmented>
	<object>
		<name>dust</name>
		<pose>Unspecified</pose>
		<truncated>0</truncated>
		<difficult>0</difficult>
		<bndbox>
			<xmin>88</xmin>
			<ymin>60</ymin>
			<xmax>179</xmax>
			<ymax>128</ymax>
		</bndbox>
	</object>
	<object>
		<name>dust</name>
		<pose>Unspecified</pose>
		<truncated>0</truncated>
		<difficult>0</difficult>
		<bndbox>
			<xmin>239</xmin>
			<ymin>20</ymin>
			<xmax>333</xmax>
			<ymax>91</ymax>
		</bndbox>
	</object>
	<object>
		<name>dust</name>
		<pose>Unspecified</pose>
		<truncated>0</truncated>
		<difficult>0</difficult>
		<bndbox>
			<xmin>212</xmin>
			<ymin>110</ymin>
			<xmax>385</xmax>
			<ymax>182</ymax>
		</bndbox>
	</object>
</annotation>
